{
  "product_id": 98,
  "product_sku": "FG-target-a-14364963",
  "company_name": "up&up",
  "retailer": "target",
  "fg_certifications": [],
  "per_ingredient": [
    {
      "rm_id": 993,
      "ingredient": "corn-oil",
      "substance": "corn-oil",
      "requirements": [
        "fda-compliant",
        "cgmp-manufactured"
      ],
      "exceptions": []
    },
    {
      "rm_id": 999,
      "ingredient": "gelatin",
      "substance": "gelatin",
      "requirements": [
        "fda-compliant",
        "cgmp-manufactured"
      ],
      "exceptions": []
    },
    {
      "rm_id": 1028,
      "ingredient": "soybean-oil",
      "substance": "soybean-oil",
      "requirements": [
        "fda-compliant",
        "cgmp-manufactured"
      ],
      "exceptions": []
    },
    {
      "rm_id": 1034,
      "ingredient": "vegetable-glycerin",
      "substance": "glycerin",
      "requirements": [
        "fda-compliant",
        "cgmp-manufactured"
      ],
      "exceptions": []
    },
    {
      "rm_id": 1040,
      "ingredient": "vitamin-d3-cholecalciferol",
      "substance": "vitamin-d3",
      "requirements": [
        "fda-compliant",
        "cgmp-manufactured"
      ],
      "exceptions": []
    }
  ],
  "total_requirements": 10,
  "required_certifications": [
    "cgmp-manufactured",
    "fda-compliant"
  ],
  "inferred_constraints": [],
  "regulatory_requirements": [
    "FDA Compliance",
    "cGMP"
  ],
  "risk_flags": [],
  "confidence": 35,
  "reasoning": "Derived 10 requirements from 0 FG certs across 5 ingredients",
  "source": "rule"
}